pybfcontrol/__init__.py
pybfcontrol/bf_button.py
pybfcontrol/bf_common.py
pybfcontrol/bf_edit.py
pybfcontrol/bf_label.py
pybfcontrol/bf_panel.py
pybfcontrol/bf_table.py
pybfcontrol/example.py
pybfcontrol/example_button.py
pybfcontrol/example_table.py
pybfcontrol/pinyin_dic.py
pybfcontrol-0.0.2.dist-info/LICENSE
pybfcontrol-0.0.2.dist-info/METADATA
pybfcontrol-0.0.2.dist-info/WHEEL
pybfcontrol-0.0.2.dist-info/top_level.txt
pybfcontrol-0.0.2.dist-info/RECORD
