Metadata-Version: 2.1
Name: pybfcontrol
Version: 0.0.2
Summary: some controls for pygame
Home-page: https://github.com/zhangenter/bf_control
Author: bitfly
Author-email: zhangbitfly@163.com
License: UNKNOWN
Platform: UNKNOWN
Classifier: Programming Language :: Python :: 3
Classifier: License :: OSI Approved :: MIT License
Classifier: Operating System :: OS Independent
Requires-Dist: pygame
